<?xml version="1.0" ?><file name="AH-1"><conversion>42.42</conversion><node><id>R43</id><type>room</type><coordinate><x>239.5</x><y>163.5</y></coordinate><connects><connection>H160</connection></connects></node><node><id>R44</id><type>room</type><coordinate><x>361.5</x><y>249.5</y></coordinate><connects><connection>H160</connection></connects></node><node><id>R45</id><type>room</type><coordinate><x>359.5</x><y>439.5</y></coordinate><connects><connection>H159</connection><connection>H158</connection></connects></node><node><id>H158</id><type>hallway</type><coordinate><x>417.5</x><y>361.5</y></coordinate><connects><connection>H168</connection><connection>R45</connection></connects></node><node><id>H159</id><type>hallway</type><coordinate><x>301.5</x><y>360.5</y></coordinate><connects><connection>R45</connection><connection>H161</connection></connects></node><node><id>H160</id><type>hallway</type><coordinate><x>308.5</x><y>252.5</y></coordinate><connects><connection>H161</connection><connection>R44</connection><connection>R43</connection></connects></node><node><id>H161</id><type>hallway</type><coordinate><x>294.5</x><y>298.5</y></coordinate><connects><connection>H159</connection><connection>H160</connection><connection>T55</connection><connection>H162</connection></connects></node><node><id>H162</id><type>hallway</type><coordinate><x>417.5</x><y>301.5</y></coordinate><connects><connection>H163</connection><connection>T56</connection><connection>H168</connection><connection>H161</connection></connects></node><node><id>H163</id><type>hallway</type><coordinate><x>418.5</x><y>236.5</y></coordinate><connects><connection>H164</connection><connection>H162</connection></connects></node><node><id>H164</id><type>hallway</type><coordinate><x>439.5</x><y>219.5</y></coordinate><connects><connection>H165</connection><connection>H163</connection></connects></node><node><id>H165</id><type>hallway</type><coordinate><x>537.5</x><y>217.5</y></coordinate><connects><connection>H166</connection><connection>H164</connection></connects></node><node><id>H166</id><type>hallway</type><coordinate><x>537.5</x><y>174.5</y></coordinate><connects><connection>T53</connection><connection>H165</connection></connects></node><node><id>H167</id><type>hallway</type><coordinate><x>454.5</x><y>345.5</y></coordinate><connects><connection>T54</connection><connection>H168</connection></connects></node><node><id>H168</id><type>hallway</type><coordinate><x>418.5</x><y>331.5</y></coordinate><connects><connection>H167</connection><connection>H162</connection><connection>H158</connection></connects></node><node><id>T53</id><type>transition</type><coordinate><x>567.5</x><y>172.5</y></coordinate><connects><connection>H166</connection></connects></node><node><id>T54</id><type>transition</type><coordinate><x>563.5</x><y>346.5</y></coordinate><connects><connection>H167</connection></connects></node><node><id>T55</id><type>transition</type><coordinate><x>238.5</x><y>300.5</y></coordinate><connects><connection>H161</connection></connects></node><node><id>T56</id><type>transition</type><coordinate><x>470.5</x><y>299.5</y></coordinate><connects><connection>H162</connection></connects></node></file>