<?xml version="1.0" ?><file name="SES-3"><conversion>42.42</conversion><node><id>R380</id><type>room</type><coordinate><x>272.2505</x><y>146.25</y></coordinate><connects><connection>H1225</connection></connects></node><node><id>R381</id><type>room</type><coordinate><x>308.75</x><y>253.0</y></coordinate><connects><connection>H1225</connection></connects></node><node><id>H1223</id><type>hallway</type><coordinate><x>232.7505</x><y>226.7505</y></coordinate><connects><connection>H1225</connection><connection>T342</connection></connects></node><node><id>H1224</id><type>hallway</type><coordinate><x>187.5005</x><y>240.5005</y></coordinate><connects><connection>T342</connection><connection>H1227</connection></connects></node><node><id>H1225</id><type>hallway</type><coordinate><x>271.5005</x><y>244.0005</y></coordinate><connects><connection>R380</connection><connection>H1223</connection><connection>H1226</connection><connection>R381</connection></connects></node><node><id>H1226</id><type>hallway</type><coordinate><x>264.5005</x><y>276.7505</y></coordinate><connects><connection>H1228</connection><connection>H1225</connection></connects></node><node><id>H1227</id><type>hallway</type><coordinate><x>262.5005</x><y>312.7505</y></coordinate><connects><connection>H1224</connection><connection>H1229</connection><connection>H1231</connection><connection>H1238</connection></connects></node><node><id>H1228</id><type>hallway</type><coordinate><x>249.2505</x><y>285.7505</y></coordinate><connects><connection>H1229</connection><connection>H1226</connection></connects></node><node><id>H1229</id><type>hallway</type><coordinate><x>263.5005</x><y>299.2505</y></coordinate><connects><connection>H1227</connection><connection>H1228</connection></connects></node><node><id>H1230</id><type>hallway</type><coordinate><x>338.0</x><y>334.0005</y></coordinate><connects><connection>H1233</connection><connection>H1237</connection><connection>T343</connection><connection>H1231</connection></connects></node><node><id>H1231</id><type>hallway</type><coordinate><x>283.5005</x><y>330.2505</y></coordinate><connects><connection>H1227</connection><connection>H1238</connection><connection>H1232</connection><connection>H1230</connection><connection>T343</connection></connects></node><node><id>H1232</id><type>hallway</type><coordinate><x>324.75</x><y>290.5005</y></coordinate><connects><connection>H1231</connection><connection>H1233</connection></connects></node><node><id>H1233</id><type>hallway</type><coordinate><x>338.75</x><y>290.7505</y></coordinate><connects><connection>H1232</connection><connection>H1230</connection><connection>H1234</connection></connects></node><node><id>H1234</id><type>hallway</type><coordinate><x>426.75</x><y>291.0005</y></coordinate><connects><connection>H1233</connection><connection>H1235</connection></connects></node><node><id>H1235</id><type>hallway</type><coordinate><x>426.25</x><y>378.5005</y></coordinate><connects><connection>H1236</connection><connection>H1237</connection><connection>H1234</connection></connects></node><node><id>H1236</id><type>hallway</type><coordinate><x>450.25</x><y>380.0005</y></coordinate><connects><connection>H1246</connection><connection>H1235</connection></connects></node><node><id>H1237</id><type>hallway</type><coordinate><x>339.5</x><y>377.2505</y></coordinate><connects><connection>H1230</connection><connection>H1238</connection><connection>H1244</connection><connection>H1235</connection></connects></node><node><id>H1238</id><type>hallway</type><coordinate><x>293.0005</x><y>359.2505</y></coordinate><connects><connection>H1227</connection><connection>H1231</connection><connection>H1239</connection><connection>H1237</connection><connection>H1261</connection></connects></node><node><id>H1239</id><type>hallway</type><coordinate><x>281.7505</x><y>365.0005</y></coordinate><connects><connection>H1238</connection><connection>H1240</connection></connects></node><node><id>H1240</id><type>hallway</type><coordinate><x>281.5005</x><y>449.5</y></coordinate><connects><connection>H1239</connection><connection>H1241</connection><connection>H1242</connection></connects></node><node><id>H1241</id><type>hallway</type><coordinate><x>238.0005</x><y>452.25</y></coordinate><connects><connection>H1240</connection><connection>T344</connection></connects></node><node><id>H1242</id><type>hallway</type><coordinate><x>313.75</x><y>449.25</y></coordinate><connects><connection>H1240</connection><connection>H1243</connection><connection>T345</connection><connection>H1258</connection><connection>T346</connection></connects></node><node><id>H1243</id><type>hallway</type><coordinate><x>316.5</x><y>428.5</y></coordinate><connects><connection>H1242</connection><connection>H1244</connection><connection>T346</connection></connects></node><node><id>H1244</id><type>hallway</type><coordinate><x>337.0</x><y>409.0</y></coordinate><connects><connection>H1237</connection><connection>H1261</connection><connection>H1243</connection><connection>H1245</connection><connection>T346</connection></connects></node><node><id>H1245</id><type>hallway</type><coordinate><x>361.0</x><y>410.25</y></coordinate><connects><connection>H1244</connection><connection>H1249</connection><connection>T346</connection></connects></node><node><id>H1246</id><type>hallway</type><coordinate><x>458.75</x><y>391.7505</y></coordinate><connects><connection>H1247</connection><connection>H1236</connection></connects></node><node><id>H1247</id><type>hallway</type><coordinate><x>457.0</x><y>420.25</y></coordinate><connects><connection>H1248</connection><connection>T347</connection><connection>H1246</connection></connects></node><node><id>H1248</id><type>hallway</type><coordinate><x>457.0</x><y>433.0</y></coordinate><connects><connection>H1250</connection><connection>H1247</connection></connects></node><node><id>H1249</id><type>hallway</type><coordinate><x>379.75</x><y>434.5</y></coordinate><connects><connection>H1245</connection><connection>H1257</connection><connection>H1250</connection><connection>T346</connection></connects></node><node><id>H1250</id><type>hallway</type><coordinate><x>414.0</x><y>435.5</y></coordinate><connects><connection>H1249</connection><connection>H1248</connection><connection>H1251</connection></connects></node><node><id>H1251</id><type>hallway</type><coordinate><x>414.5</x><y>522.0</y></coordinate><connects><connection>H1252</connection><connection>H1250</connection></connects></node><node><id>H1252</id><type>hallway</type><coordinate><x>411.75</x><y>544.25</y></coordinate><connects><connection>H1253</connection><connection>H1251</connection></connects></node><node><id>H1253</id><type>hallway</type><coordinate><x>397.0</x><y>552.25</y></coordinate><connects><connection>H1254</connection><connection>H1252</connection></connects></node><node><id>H1254</id><type>hallway</type><coordinate><x>359.0</x><y>550.75</y></coordinate><connects><connection>H1255</connection><connection>T348</connection><connection>H1253</connection></connects></node><node><id>H1255</id><type>hallway</type><coordinate><x>353.25</x><y>504.0</y></coordinate><connects><connection>H1256</connection><connection>H1254</connection><connection>H1259</connection></connects></node><node><id>H1256</id><type>hallway</type><coordinate><x>354.5</x><y>473.5</y></coordinate><connects><connection>H1257</connection><connection>H1258</connection><connection>H1255</connection><connection>T346</connection></connects></node><node><id>H1257</id><type>hallway</type><coordinate><x>377.25</x><y>455.75</y></coordinate><connects><connection>H1249</connection><connection>H1256</connection><connection>T346</connection></connects></node><node><id>H1258</id><type>hallway</type><coordinate><x>333.25</x><y>472.75</y></coordinate><connects><connection>H1256</connection><connection>H1242</connection><connection>T346</connection></connects></node><node><id>H1259</id><type>hallway</type><coordinate><x>244.0005</x><y>502.5</y></coordinate><connects><connection>H1255</connection><connection>H1260</connection></connects></node><node><id>H1260</id><type>hallway</type><coordinate><x>236.5005</x><y>491.75</y></coordinate><connects><connection>H1259</connection><connection>T344</connection></connects></node><node><id>H1261</id><type>hallway</type><coordinate><x>319.0</x><y>378.334</y></coordinate><connects><connection>H1238</connection><connection>H1244</connection></connects></node><node><id>T342</id><type>transition</type><coordinate><x>215.2988</x><y>209.3301</y></coordinate><connects><connection>H1223</connection><connection>H1224</connection></connects></node><node><id>T343</id><type>transition</type><coordinate><x>321.5</x><y>325.25</y></coordinate><connects><connection>H1230</connection><connection>H1231</connection></connects></node><node><id>T344</id><type>transition</type><coordinate><x>234.5</x><y>468.75</y></coordinate><connects><connection>H1241</connection><connection>H1260</connection></connects></node><node><id>T345</id><type>transition</type><coordinate><x>302.75</x><y>436.0</y></coordinate><connects><connection>H1242</connection></connects></node><node><id>T346</id><type>transition</type><coordinate><x>345.75</x><y>441.0</y></coordinate><connects><connection>H1244</connection><connection>H1245</connection><connection>H1249</connection><connection>H1257</connection><connection>H1256</connection><connection>H1258</connection><connection>H1242</connection><connection>H1243</connection></connects></node><node><id>T347</id><type>transition</type><coordinate><x>466.25</x><y>411.0</y></coordinate><connects><connection>H1247</connection></connects></node><node><id>T348</id><type>transition</type><coordinate><x>377.75</x><y>559.25</y></coordinate><connects><connection>H1254</connection></connects></node></file>